{"cameraMode":{"drawMode":0,"name":"Shaded","section":"Shading Mode"},"sceneLighting":false,"audioPlay":false,"sceneViewState":{"m_AlwaysRefresh":false,"showFog":true,"showSkybox":false,"showFlares":true,"showImageEffects":true,"showParticleSystems":true,"showVisualEffectGraphs":true,"m_FxEnabled":true},"in2DMode":false,"pivot":{"x":-10.25,"y":2.0,"z":-0.2499999850988388},"rotation":{"x":0.21399571001529694,"y":0.07463987171649933,"z":-0.016401808708906175,"w":0.9738245010375977},"size":0.8626116514205933,"orthographic":false}